<?xml version="1.0" encoding="UTF-8"?>
<objects serializationModel="Studio.02.01.00">
	<object class="AudioFile" id="{72cf604d-27c3-46de-b515-6ebd9483dd0f}">
		<property name="assetPath">
			<value>sfx_gameplay_redsoulflwng_scream1.wav</value>
		</property>
		<property name="frequencyInKHz">
			<value>44.0999985</value>
		</property>
		<property name="channelCount">
			<value>2</value>
		</property>
		<property name="length">
			<value>5</value>
		</property>
		<relationship name="masterAssetFolder">
			<destination>{f3d90f75-1531-4369-b696-f03b5bdb950d}</destination>
		</relationship>
	</object>
</objects>
